psdq/__init__.py
psdq/pysparkdq.py
psdq-1.0.1.dist-info/licenses/LICENSE
tests/__init__.py
tests/conftest.py
tests/test_pysparkdq.py
psdq-1.0.1.dist-info/METADATA
psdq-1.0.1.dist-info/WHEEL
psdq-1.0.1.dist-info/top_level.txt
psdq-1.0.1.dist-info/RECORD
