Metadata-Version: 2.4
Name: psdq
Version: 1.0.1
Summary: Ad Hoc Data Quality Tool for PySpark
Author: Alexandre "Alex" de Magalhaes
Author-email: alexandredemagalhaess@gmail.com
Requires-Python: >=3.9
License-File: LICENSE
Requires-Dist: pyspark>=3.0.0
Dynamic: author
Dynamic: author-email
Dynamic: description
Dynamic: description-content-type
Dynamic: license-file
Dynamic: requires-dist
Dynamic: requires-python
Dynamic: summary
